[
    {
        "code": "CISC 360",
        "name": "Computer Architecture",
        "descr": "",
        "credits": "3",
        "preReq": "",
        "restrict": "",
        "breadth": "",
        "typ": ""
    },
    {
        "code": "CISC 361",
        "name": "Operating Systems",
        "descr": "",
        "credits": "3",
        "preReq": "",
        "restrict": "",
        "breadth": "",
        "typ": ""
    },
    {
        "code": "CISC 372",
        "name": "Parallel Computing",
        "descr": "",
        "credits": "3",
        "preReq": "",
        "restrict": "",
        "breadth": "",
        "typ": ""
    },
    {
        "code": "CISC 450",
        "name": "Computer Networks I",
        "descr": "",
        "credits": "3",
        "preReq": "",
        "restrict": "",
        "breadth": "",
        "typ": ""
    },
    {
        "code": "CISC 471",
        "name": "Compiler Design",
        "descr": "",
        "credits": "3",
        "preReq": "",
        "restrict": "",
        "breadth": "",
        "typ": ""
    }
]